{
    "description": "AdoptOpenJDK 11 JRE with Oracle HotSpot JVM (Nightly builds)",
    "homepage": "https://adoptopenjdk.net",
    "version": "201909170816",
    "license": "GPL-2.0-only WITH Classpath-exception-2.0",
    "architecture": {
        "64bit": {
            "url": "https://github.com/AdoptOpenJDK/openjdk11-binaries/releases/download/jdk11u-2019-09-17-08-16/OpenJDK11U-jre_x64_windows_hotspot_2019-09-17-08-16.zip",
            "hash": "ab7f5ff4b5953681d5c486c813cc0e6229b4222687401e5e454c7bed08684bb2"
        },
        "32bit": {
            "url": "https://github.com/AdoptOpenJDK/openjdk11-binaries/releases/download/jdk11u-2019-09-17-08-16/OpenJDK11U-jre_x86-32_windows_hotspot_2019-09-17-08-16.zip",
            "hash": "f95fdd47c32a4ac2622b320093541cab673df0f4fb5026f195fad5c1985fc58e"
        }
    },
    "extract_to": "tmp",
    "installer": {
        "script": [
            "(Get-ChildItem -Directory \"$dir\\tmp\").FullName | % { Move-Item \"$_\\*\" \"$dir\" }",
            "Remove-Item -Recurse \"$dir\\tmp\""
        ]
    },
    "env_add_path": "bin",
    "env_set": {
        "JAVA_HOME": "$dir"
    },
    "checkver": {
        "url": "https://api.adoptopenjdk.net/v2/info/nightly/openjdk11?openjdk_impl=hotspot&os=windows&arch=x64&release=latest&type=jre",
        "jp": "$.binaries[0].binary_link",
        "re": "https://github.com/(?<url>.*?jdk(?<major>[\\d]+)u-(?<date>(?<year>[\\d]{4})-(?<month>[\\d]{2})-(?<day>[\\d]{2})-(?<hour>[\\d]{2})-(?<minute>[\\d]{2})))",
        "replace": "${year}${month}${day}${hour}${minute}"
    },
    "autoupdate": {
        "architecture": {
            "64bit": {
                "url": "https://github.com/$matchUrl/OpenJDK$matchMajorU-jre_x64_windows_hotspot_$matchDate.zip"
            },
            "32bit": {
                "url": "https://github.com/$matchUrl/OpenJDK$matchMajorU-jre_x86-32_windows_hotspot_$matchDate.zip"
            }
        },
        "hash": {
            "url": "$url.sha256.txt",
            "find": "^([a-fA-F0-9]+)\\s"
        }
    }
}
