{
    "homepage": "https://adoptopenjdk.net",
    "version": "8u172-b00-20180509",
    "license": "http://openjdk.java.net/legal/gplv2+ce.html",
    "architecture": {
        "64bit": {
            "url": "https://github.com/AdoptOpenJDK/openjdk8-nightly/releases/download/jdk8u172-b00-20180509/OpenJDK8_x64_Win_20180509.zip",
            "hash": "a0b0880c062bf4fa1c80e09746f66768cbc3ee7c63f74638dc1b57346aa436ff"
        }
    },
    "extract_dir": "jdk8u172-b03",
    "env_add_path": "bin",
    "env_set": {
        "JAVA_HOME": "$dir"
    },
    "checkver": {
        "github": "https://github.com/AdoptOpenJDK/openjdk8-nightly",
        "re": "(?<fullname>jdk(?<major>[\\du]+)-(?<build>b[\\d]+)-(?<bdate>[\\d]{8}))",
        "replace": "${major}-${build}-${bdate}"
    },
    "autoupdate": {
        "architecture": {
            "64bit": {
                "url": "https://github.com/AdoptOpenJDK/openjdk8-nightly/releases/download/$matchFullname/OpenJDK8_x64_Win_$matchBdate.zip",
                "hash": {
                    "url": "https://github.com/AdoptOpenJDK/openjdk8-nightly/releases/download/$matchFullname/OpenJDK8_x64_Win_$matchBdate.sha256.txt",
                    "find": "^([a-fA-F0-9]{64})"
                }
            }
        },
        "extract_dir": "jdk$matchMajor-b03"
    }
}
